metad/__init__.py
metad/__main__.py
metad/metadata.py
metad/schema.json
metad/connectors/__init__.py
metad/connectors/base.py
metad/connectors/dataframe.py
metad/connectors/mysql.py
metad-0.0.2.dist-info/AUTHORS.rst
metad-0.0.2.dist-info/LICENSE
metad-0.0.2.dist-info/METADATA
metad-0.0.2.dist-info/WHEEL
metad-0.0.2.dist-info/entry_points.txt
metad-0.0.2.dist-info/top_level.txt
metad-0.0.2.dist-info/RECORD
