Metadata-Version: 2.1
Name: metad
Version: 0.0.2
Summary: A hierarchical representation for the structure of a relational database.
Home-page: https://github.com/data-dev/MetaData
Author: MIT Data To AI Lab
Author-email: dailabmit@gmail.com
License: MIT license
Keywords: metad metad MetaData
Platform: UNKNOWN
Classifier: Development Status :: 2 - Pre-Alpha
Classifier: Intended Audience :: Developers
Classifier: License :: OSI Approved :: MIT License
Classifier: Natural Language :: English
Classifier: Programming Language :: Python :: 3
Classifier: Programming Language :: Python :: 3.5
Classifier: Programming Language :: Python :: 3.6
Classifier: Programming Language :: Python :: 3.7
Classifier: Programming Language :: Python :: 3.8
Requires-Python: >=3.5
Requires-Dist: docopt
Requires-Dist: pandas
Requires-Dist: pymysql
Requires-Dist: fastjsonschema
Requires-Dist: parameterized
Provides-Extra: dev
Requires-Dist: bumpversion (>=0.5.3) ; extra == 'dev'
Requires-Dist: pip (>=9.0.1) ; extra == 'dev'
Requires-Dist: watchdog (>=0.8.3) ; extra == 'dev'
Requires-Dist: m2r (<0.3,>=0.2.0) ; extra == 'dev'
Requires-Dist: Sphinx (<3,>=1.7.1) ; extra == 'dev'
Requires-Dist: sphinx-rtd-theme (<0.5,>=0.2.4) ; extra == 'dev'
Requires-Dist: autodocsumm (>=0.1.10) ; extra == 'dev'
Requires-Dist: flake8 (>=3.7.7) ; extra == 'dev'
Requires-Dist: isort (>=4.3.4) ; extra == 'dev'
Requires-Dist: autoflake (>=1.2) ; extra == 'dev'
Requires-Dist: autopep8 (>=1.4.3) ; extra == 'dev'
Requires-Dist: twine (>=1.10.0) ; extra == 'dev'
Requires-Dist: wheel (>=0.30.0) ; extra == 'dev'
Requires-Dist: coverage (>=4.5.1) ; extra == 'dev'
Requires-Dist: tox (>=2.9.1) ; extra == 'dev'
Requires-Dist: pytest (>=3.4.2) ; extra == 'dev'
Requires-Dist: pytest-cov (>=2.6.0) ; extra == 'dev'
Requires-Dist: rundoc (<0.5,>=0.4.3) ; extra == 'dev'
Provides-Extra: test
Requires-Dist: pytest (>=3.4.2) ; extra == 'test'
Requires-Dist: pytest-cov (>=2.6.0) ; extra == 'test'
Requires-Dist: rundoc (<0.5,>=0.4.3) ; extra == 'test'
